{
  "$schema": "https://www.mintlify.com/schema.json",
  "name": "MyCrumbsUI",
  "logo": {
    "dark": "./logo/dark.png",
    "light": "./logo/light.png"
  },
  "favicon": "./favicon.png",
  "colors": {
    "primary": "#3b82f6",
    "light": "#1d4ed8",
    "dark": "#3b82f6",
    "anchors": {
      "from": "#1d4ed8",
      "to": "#bfdbfe"
    }
  },
  "topbarLinks": [
    {
      "name": "Support",
      "url": "mailto:nikoemme@skiff.com"
    }
  ],
  "topbarCtaButton": {
    "name": "Website",
    "url": "https://mycrumbs.xyz"
  },
  
  "anchors": [
  
   
    {
      "name": "Components",
      "icon": "slack",
      "url": "components"
    }
    
  ],
  "navigation": [
   
    {
      "group": "Components",
      "pages": [
        "components/3DCard",
        "components/Alert",
        "components/Button",
        "components/Card",
        "components/Checkbox",
        "components/Collapse",
        "components/GridLayout",
        "components/HelpTooltip",
        "components/Image",
        "components/Input",
        "components/Modal",
        "components/Select",
        "components/Spinner",
        "components/TextArea",
        "components/Toggle"
      ]
    }
   
  ],
  "footerSocials": {
    "x": "https://x.com/nikomatt69",
    "github": "https://github.com/nikomatt69"

  }
}